fhetalib/__init__.py
fhetalib-1.7.0.0.dist-info/METADATA
fhetalib-1.7.0.0.dist-info/WHEEL
fhetalib-1.7.0.0.dist-info/top_level.txt
fhetalib-1.7.0.0.dist-info/RECORD
