Metadata-Version: 2.1
Name: fhetalib
Version: 1.7.0.0
Author: FHeta
Classifier: Programming Language :: Python :: 3
Classifier: License :: OSI Approved :: MIT License
Classifier: Operating System :: OS Independent
Requires-Python: >=3.6
Requires-Dist: telethon
Requires-Dist: requests
Requires-Dist: flask
